p2/__init__.py
p2/cmd.py
p2-1.0.1.dist-info/METADATA
p2-1.0.1.dist-info/RECORD
p2-1.0.1.dist-info/WHEEL
p2-1.0.1.dist-info/entry_points.txt
p2-1.0.1.dist-info/top_level.txt
