Metadata-Version: 2.1
Name: p2
Version: 1.0.1
Summary: Rerun command by watching modified file
Home-page: https://github.com/keitheis/p2
Author: Keith Yang
Author-email: yang@keitheis.org
License: MIT License
Keywords: keitheis
Platform: UNKNOWN
Classifier: Development Status :: 5 - Production/Stable
Classifier: Intended Audience :: Developers
Classifier: License :: OSI Approved :: MIT License
Classifier: Programming Language :: Python :: 2.7
Classifier: Programming Language :: Python :: 3.3
Classifier: Programming Language :: Python :: 3.4
Classifier: Programming Language :: Python :: 3.5
Classifier: Programming Language :: Python :: 3.6
